README.md
setup.py
efficientunet/__init__.py
efficientunet/_version.py
efficientunet/efficientnet.py
efficientunet/efficientunet.py
efficientunet/layers.py
efficientunet/utils.py
efficientunet_pytorch.egg-info/PKG-INFO
efficientunet_pytorch.egg-info/SOURCES.txt
efficientunet_pytorch.egg-info/dependency_links.txt
efficientunet_pytorch.egg-info/not-zip-safe
efficientunet_pytorch.egg-info/requires.txt
efficientunet_pytorch.egg-info/top_level.txt